{"users":{"1227525348":{"name":"M\u00e1ster Formatos UV","screen_name":"MsterFormatosUV","location":"Valencia, Espa\u00f1a","followers_count":105,"profile_image_url":"http:\/\/pbs.twimg.com\/profile_images\/444551560333242368\/YzwkdyLO_normal.png","net":"tw"}},"total":1,"search":[{"user":"1227525348","screen_name":"MsterFormatosUV","text":"17 nominaciones convierte a #LaIslaM\u00ednima en favorita para los #Goya2015. Este es el enlace con todos los nominados: http:\/\/t.co\/FxHDJidS1s","id":"558727531038527488","link":"http:\/\/twitter.com\/MsterFormatosUV\/status\/558727531038527488","net":"tw","tags":["telediario","teledeporte"]}]}